evetech/__init__.py
evetech/lib.py
evetech-2.1.2.dist-info/licenses/LICENSE
evetech-2.1.2.dist-info/METADATA
evetech-2.1.2.dist-info/WHEEL
evetech-2.1.2.dist-info/top_level.txt
evetech-2.1.2.dist-info/RECORD
